dataclass_builder/__init__.py
dataclass_builder/__version__.py
dataclass_builder/_common.py
dataclass_builder/exceptions.py
dataclass_builder/factory.py
dataclass_builder/py.typed
dataclass_builder/utility.py
dataclass_builder/wrapper.py
tests/__init__.py
tests/conftest.py
tests/test_common.py
tests/test_factory.py
tests/test_utility.py
tests/test_wrapper.py
dataclass_builder-1.2.0.dist-info/LICENSE
dataclass_builder-1.2.0.dist-info/METADATA
dataclass_builder-1.2.0.dist-info/WHEEL
dataclass_builder-1.2.0.dist-info/top_level.txt
dataclass_builder-1.2.0.dist-info/RECORD
