Metadata-Version: 2.1
Name: dataclass-builder
Version: 1.2.0
Summary: Create instances of dataclasses with the builder pattern.
Home-page: https://github.com/mrshannon/dataclass-builder
Author: Michael R. Shannon
Author-email: mrshannon.aerospace@gmail.com
License: MIT
Platform: UNKNOWN
Classifier: Development Status :: 5 - Production/Stable
Classifier: Intended Audience :: Developers
Classifier: License :: OSI Approved :: MIT License
Classifier: Programming Language :: Python
Classifier: Programming Language :: Python :: 3
Classifier: Programming Language :: Python :: 3.6
Classifier: Programming Language :: Python :: 3.7
Classifier: Topic :: Software Development :: Libraries
Requires-Dist: dataclasses ; python_version == "3.6"
Provides-Extra: checks
Requires-Dist: flake8 (>=3.7.7) ; extra == 'checks'
Requires-Dist: flake8-bugbear ; extra == 'checks'
Requires-Dist: mypy ; extra == 'checks'
Requires-Dist: pydocstyle ; extra == 'checks'
Provides-Extra: dev
Requires-Dist: black ; extra == 'dev'
Requires-Dist: isort ; extra == 'dev'
Requires-Dist: twine ; extra == 'dev'
Requires-Dist: flake8 (>=3.7.7) ; extra == 'dev'
Requires-Dist: flake8-bugbear ; extra == 'dev'
Requires-Dist: mypy ; extra == 'dev'
Requires-Dist: pydocstyle ; extra == 'dev'
Requires-Dist: pytest ; extra == 'dev'
Requires-Dist: pytest-cov ; extra == 'dev'
Requires-Dist: pytest-mock ; extra == 'dev'
Requires-Dist: packaging ; extra == 'dev'
Requires-Dist: sphinx (>=1.7) ; extra == 'dev'
Requires-Dist: sphinxcontrib-apidoc ; extra == 'dev'
Provides-Extra: docs
Requires-Dist: packaging ; extra == 'docs'
Requires-Dist: sphinx (>=1.7) ; extra == 'docs'
Requires-Dist: sphinxcontrib-apidoc ; extra == 'docs'
Provides-Extra: tests
Requires-Dist: pytest ; extra == 'tests'
Requires-Dist: pytest-cov ; extra == 'tests'
Requires-Dist: pytest-mock ; extra == 'tests'
